README.md
setup.py
label/__init__.py
label/label.py
label/prompt.py
label.egg-info/PKG-INFO
label.egg-info/SOURCES.txt
label.egg-info/dependency_links.txt
label.egg-info/not-zip-safe
label.egg-info/top_level.txt