Metadata-Version: 1.0
Name: label
Version: 0.1.1
Summary: Labeling for supervised learning
Home-page: https://github.com/aslanreut/label
Author: Aslan Reut
Author-email: UNKNOWN
License: MIT
Platform: UNKNOWN
